segmetrics/__init__.py
segmetric-0.0.1.dist-info/LICENSE
segmetric-0.0.1.dist-info/METADATA
segmetric-0.0.1.dist-info/WHEEL
segmetric-0.0.1.dist-info/top_level.txt
segmetric-0.0.1.dist-info/RECORD
